gico/gico.py
gico-1.0.7.dist-info/METADATA
gico-1.0.7.dist-info/WHEEL
gico-1.0.7.dist-info/entry_points.txt
gico-1.0.7.dist-info/top_level.txt
gico-1.0.7.dist-info/RECORD
