Metadata-Version: 2.1
Name: gico
Version: 1.0.7
Summary: Gico makes your git history consistent, and your changes -- traceable
Home-page: https://github.com/damurashov/TIRED
Author: Dmitry Murashov
License: MIT
Classifier: Programming Language :: Python :: 3
Classifier: License :: OSI Approved :: MIT License
Classifier: Operating System :: OS Independent
Requires-Python: >=3.7
Requires-Dist: tired
